<?xml version="1.0"?>

<!-- ** NOT FOR NAVIGATION ** ** FOR SIMULATION PUROSES ONLY ** -->
<!-- FG OpenRadar Procedure generated by xmly.py -->
<!-- procAAll typeAAll for KBOS -->

<routes>

  <addPoint code="GDM" point="42.545917,-72.058194"/>
  <addPoint code="BRONC" point="42.514972,-71.722667"/>
  <addPoint code="LOBBY" point="42.504306,-71.609444"/>
  <addPoint code="SOSYO" point="42.487361,-71.432167"/>
  <addPoint code="REVER" point="42.440972,-70.961472"/>
  <addPoint code="BOS" point="42.357444,-70.989556"/>
  <addPoint code="PVD" point="41.724333,-71.429639"/>
  <addPoint code="KRANN" point="41.855194,-71.123472"/>
  <addPoint code="EURRO" point="42.650750,-70.087944"/>
  <addPoint code="OOSHN" point="42.601500,-70.231222"/>
  <addPoint code="TTERI" point="42.529583,-70.515250"/>
  <addPoint code="WAATR" point="42.457833,-70.825556"/>
  <addPoint code="FLUTI" point="42.412417,-70.886639"/>
  <addPoint code="GRIFI" point="42.311722,-70.934917"/>
  <addPoint code="GGABE" point="42.274806,-70.950917"/>
  <addPoint code="JOBEE" point="42.178333,-70.992278"/>
  <addPoint code="PLGRM" point="42.387611,-70.855500"/>
  <addPoint code="BECHH" point="42.336889,-70.837917"/>
  <addPoint code="SCITU" point="42.278750,-70.760611"/>
  <addPoint code="GRGIO" point="42.585944,-70.565111"/>
  <addPoint code="BRGIT" point="42.556972,-70.697861"/>
  <addPoint code="ADDDA" point="42.605639,-70.782083"/>
  <addPoint code="LEEZI" point="42.683944,-70.743417"/>
  <addPoint code="HNOVR" point="42.535389,-70.829972"/>
  <addPoint code="PUDJJ" point="42.480167,-70.296861"/>
  <addPoint code="AYBEE" point="42.440556,-70.527917"/>
  <addPoint code="QUABN" point="42.481861,-71.375778"/>
  <addPoint code="RSVOR" point="42.461333,-71.156028"/>
  <addPoint code="MISTK" point="42.449583,-71.027028"/>
  <addPoint code="CHYAN" point="42.496222,-71.060889"/>
  <addPoint code="HILLL" point="42.582389,-71.018417"/>
  <addPoint code="FAKKE" point="42.468028,-70.785056"/>
  <addPoint code="BRODI" point="42.386944,-70.921750"/>
  <addPoint code="ROBUC" point="41.678917,-71.585111"/>
  <addPoint code="PROVI" point="41.723750,-71.431722"/>
  <addPoint code="JOODY" point="41.785389,-71.287556"/>
  <addPoint code="SOFEE" point="41.843167,-71.258917"/>
  <addPoint code="ERNEI" point="41.944806,-71.208528"/>
  <addPoint code="NUNZO" point="42.030889,-71.203722"/>
  <addPoint code="GOSHI" point="42.036417,-71.163083"/>
  <addPoint code="ANSLY" point="41.923889,-70.971889"/>
  <addPoint code="CRADL" point="42.010250,-70.763222"/>
  <addPoint code="KLEBB" point="42.108417,-70.616139"/>
  <addPoint code="ETHYN" point="42.325861,-70.555444"/>
  <addPoint code="PTRIK" point="42.527278,-70.820639"/>
  <addPoint code="TAALE" point="42.626278,-70.771861"/>
  <addPoint code="BEREI" point="42.008917,-70.805750"/>
  <addPoint code="BBOGG" point="42.099167,-70.685861"/>
  <addPoint code="HOKDU" point="42.345528,-70.565500"/>
  <addPoint code="ORW" point="41.556417,-71.999361"/>
  <addPoint code="JEWIT" point="41.696083,-71.825889"/>
  <addPoint code="FOSTY" point="41.843194,-71.642028"/>
  <addPoint code="HEFTY" point="41.905333,-71.564000"/>
  <addPoint code="WOONS" point="41.950583,-71.507028"/>
  <addPoint code="NHANT" point="42.439778,-70.966667"/>
  <addPoint code="HURBE" point="42.460750,-70.851944"/>
  <addPoint code="ORRRR" point="42.424583,-70.753722"/>
  <addPoint code="CHWDH" point="42.304306,-70.729694"/>
  <addPoint code="STEEM" point="42.242028,-70.825639"/>
  <addPoint code="DEDHM" point="42.195639,-70.949167"/>
  <addPoint code="BLZZR" point="42.217333,-71.760167"/>
  <addPoint code="CLAWW" point="42.390361,-70.813250"/>
  <addPoint code="FENWY" point="42.377333,-70.727833"/>
  <addPoint code="GLLET" point="42.273361,-70.722583"/>
  <addPoint code="WYMTH" point="42.212222,-70.827111"/>
  <addPoint code="FOXXX" point="42.315361,-70.902917"/>
  <addPoint code="BRRRO" point="42.333556,-70.801528"/>
  <addPoint code="JAITE" point="42.303583,-70.713750"/>
  <addPoint code="HEWMO" point="42.187861,-70.733472"/>
  <addPoint code="KENWI" point="42.159694,-70.940833"/>
  <addPoint code="TJAYY" point="42.305056,-70.960500"/>
  <addPoint code="KIRAA" point="42.275417,-71.128278"/>
  <addPoint code="TEKKK" point="42.412750,-71.098639"/>
  <addPoint code="EXXXX" point="42.343639,-71.351278"/>
  <addPoint code="BUCYK" point="42.293361,-70.683750"/>
  <addPoint code="BRUWN" point="41.602694,-70.229389"/>
  <addPoint code="COLYN" point="42.152694,-71.040111"/>
  <addPoint code="COUSY" point="42.354972,-71.208806"/>
  <addPoint code="CBEAR" point="42.255528,-71.160083"/>
  <addPoint code="TONNI" point="42.373361,-70.613528"/>
  <addPoint code="CELTK" point="42.266417,-70.103417"/>
  <addPoint code="SCOAR" point="42.312611,-70.637500"/>
  <addPoint code="STAYC" point="42.507833,-70.791556"/>
  <addPoint code="SHAAN" point="42.579889,-70.827611"/>
  <addPoint code="HYLND" point="42.780861,-71.275306"/>
  <addPoint code="CORRT" point="42.445944,-70.759778"/>
  <addPoint code="BOATT" point="42.342111,-70.753806"/>
  <addPoint code="HEARR" point="42.447028,-70.709750"/>
  <addPoint code="MARBB" point="42.533528,-70.765917"/>
  <addPoint code="GLOWB" point="42.289389,-71.218389"/>
  <addPoint code="HRALD" point="42.380083,-71.257972"/>
  <addPoint code="CAMWI" point="42.511667,-71.152667"/>
  <addPoint code="SHAUN" point="42.676167,-70.640861"/>
  <addPoint code="LBSTA" point="42.800000,-70.613528"/>
  <addPoint code="CLMPP" point="42.479917,-70.726444"/>
  <addPoint code="PATSS" point="42.089083,-71.710833"/>
  <addPoint code="REVSS" point="42.345444,-71.810306"/>
  <addPoint code="DUBYU" point="42.395722,-71.345694"/>
  <addPoint code="JSTER" point="42.139389,-70.613194"/>
  <addPoint code="SSOXS" point="41.836833,-70.746194"/>
  <addPoint code="WYLYY" point="42.300833,-71.100667"/>
  <addPoint code="CYOTI" point="42.156611,-71.257111"/>

  <route name="OOSHN3" displayMode="star" zoomMin="8" zoomMax="600" color="160,200,240">
    <activeLandingRunways>04L</activeLandingRunways>
    <navaids>EURRO,OOSHN,TTERI,WAATR,FLUTI,GRIFI,GGABE,JOBEE</navaids>
    <line start="EURRO" end="OOSHN" arrows="end" stroke="1-6-2-3" color="20,140,240" />
    <line start="OOSHN" end="TTERI" arrows="end" stroke="1-6-2-3" color="20,140,240" />
    <line start="TTERI" end="WAATR" arrows="end" stroke="1-6-2-3" color="20,140,240" />
    <line start="WAATR" end="FLUTI" arrows="end" stroke="1-6-2-3" color="20,140,240" />
    <line start="FLUTI" end="GRIFI" arrows="end" stroke="1-6-2-3" color="20,140,240" />
    <line start="GRIFI" end="GGABE" arrows="end" stroke="1-6-2-3" color="20,140,240" />
    <line start="GGABE" end="JOBEE" arrows="end" stroke="1-6-2-3" color="20,140,240" />
  </route>

  <route name="OOSHN3" displayMode="star" zoomMin="8" zoomMax="600" color="160,200,240">
    <activeLandingRunways>04R</activeLandingRunways>
    <navaids>EURRO,OOSHN,TTERI,WAATR,FLUTI,GRIFI,GGABE,JOBEE</navaids>
    <line start="EURRO" end="OOSHN" arrows="end" stroke="1-6-2-3" color="20,140,240" />
    <line start="OOSHN" end="TTERI" arrows="end" stroke="1-6-2-3" color="20,140,240" />
    <line start="TTERI" end="WAATR" arrows="end" stroke="1-6-2-3" color="20,140,240" />
    <line start="WAATR" end="FLUTI" arrows="end" stroke="1-6-2-3" color="20,140,240" />
    <line start="FLUTI" end="GRIFI" arrows="end" stroke="1-6-2-3" color="20,140,240" />
    <line start="GRIFI" end="GGABE" arrows="end" stroke="1-6-2-3" color="20,140,240" />
    <line start="GGABE" end="JOBEE" arrows="end" stroke="1-6-2-3" color="20,140,240" />
  </route>

  <route name="OOSHN3" displayMode="star" zoomMin="8" zoomMax="600" color="160,200,240">
    <activeLandingRunways>33L</activeLandingRunways>
    <navaids>EURRO,OOSHN,TTERI,WAATR,PLGRM,BECHH,SCITU</navaids>
    <line start="EURRO" end="OOSHN" arrows="end" stroke="1-5-2-4" color="20,200,240" />
    <line start="OOSHN" end="TTERI" arrows="end" stroke="1-5-2-4" color="20,200,240" />
    <line start="TTERI" end="WAATR" arrows="end" stroke="1-5-2-4" color="20,200,240" />
    <line start="WAATR" end="PLGRM" arrows="end" stroke="1-5-2-4" color="20,200,240" />
    <line start="PLGRM" end="BECHH" arrows="end" stroke="1-5-2-4" color="20,200,240" />
    <line start="BECHH" end="SCITU" arrows="end" stroke="1-5-2-4" color="20,200,240" />
  </route>

  <route name="OOSHN3" displayMode="star" zoomMin="8" zoomMax="600" color="160,200,240">
    <activeLandingRunways>32</activeLandingRunways>
    <navaids>EURRO,OOSHN,TTERI,WAATR,PLGRM,BECHH,SCITU</navaids>
    <line start="EURRO" end="OOSHN" arrows="end" stroke="1-5-2-4" color="20,200,240" />
    <line start="OOSHN" end="TTERI" arrows="end" stroke="1-5-2-4" color="20,200,240" />
    <line start="TTERI" end="WAATR" arrows="end" stroke="1-5-2-4" color="20,200,240" />
    <line start="WAATR" end="PLGRM" arrows="end" stroke="1-5-2-4" color="20,200,240" />
    <line start="PLGRM" end="BECHH" arrows="end" stroke="1-5-2-4" color="20,200,240" />
    <line start="BECHH" end="SCITU" arrows="end" stroke="1-5-2-4" color="20,200,240" />
  </route>

  <route name="OOSHN3" displayMode="star" zoomMin="8" zoomMax="600" color="160,200,240">
    <activeLandingRunways>22L</activeLandingRunways>
    <navaids>EURRO,OOSHN,GRGIO,BRGIT,ADDDA,LEEZI</navaids>
    <line start="EURRO" end="OOSHN" arrows="end" stroke="1-4-2-5" color="80,20,240" />
    <line start="OOSHN" end="GRGIO" arrows="end" stroke="1-4-2-5" color="80,20,240" />
    <line start="GRGIO" end="BRGIT" arrows="end" stroke="1-4-2-5" color="80,20,240" />
    <line start="BRGIT" end="ADDDA" arrows="end" stroke="1-4-2-5" color="80,20,240" />
    <line start="ADDDA" end="LEEZI" arrows="end" stroke="1-4-2-5" color="80,20,240" />
  </route>

  <route name="OOSHN3" displayMode="star" zoomMin="8" zoomMax="600" color="160,200,240">
    <activeLandingRunways>15R</activeLandingRunways>
    <navaids>EURRO,OOSHN,GRGIO,BRGIT,HNOVR</navaids>
    <line start="EURRO" end="OOSHN" arrows="end" stroke="1-3-2-6" color="80,80,240" />
    <line start="OOSHN" end="GRGIO" arrows="end" stroke="1-3-2-6" color="80,80,240" />
    <line start="GRGIO" end="BRGIT" arrows="end" stroke="1-3-2-6" color="80,80,240" />
    <line start="BRGIT" end="HNOVR" arrows="end" stroke="1-3-2-6" color="80,80,240" />
  </route>

  <route name="OOSHN3" displayMode="star" zoomMin="8" zoomMax="600" color="160,200,240">
    <activeLandingRunways>27</activeLandingRunways>
    <navaids>EURRO,OOSHN,PUDJJ,AYBEE</navaids>
    <line start="EURRO" end="OOSHN" arrows="end" stroke="1-2-2-7" color="80,140,240" />
    <line start="OOSHN" end="PUDJJ" arrows="end" stroke="1-2-2-7" color="80,140,240" />
    <line start="PUDJJ" end="AYBEE" arrows="end" stroke="1-2-2-7" color="80,140,240" />
  </route>

  <route name="QUABN3" displayMode="star" zoomMin="8" zoomMax="600" color="160,200,240">
    <activeLandingRunways>04L</activeLandingRunways>
    <navaids>QUABN,RSVOR,MISTK,GRIFI,GGABE,JOBEE</navaids>
    <line start="QUABN" end="RSVOR" arrows="end" stroke="1-1-2-8" color="80,200,240" />
    <line start="RSVOR" end="MISTK" arrows="end" stroke="1-1-2-8" color="80,200,240" />
    <line start="MISTK" end="GRIFI" arrows="end" stroke="1-1-2-8" color="80,200,240" />
    <line start="GRIFI" end="GGABE" arrows="end" stroke="1-1-2-8" color="80,200,240" />
    <line start="GGABE" end="JOBEE" arrows="end" stroke="1-1-2-8" color="80,200,240" />
  </route>

  <route name="QUABN3" displayMode="star" zoomMin="8" zoomMax="600" color="160,200,240">
    <activeLandingRunways>04R</activeLandingRunways>
    <navaids>QUABN,RSVOR,MISTK,GRIFI,GGABE,JOBEE</navaids>
    <line start="QUABN" end="RSVOR" arrows="end" stroke="1-1-2-8" color="80,200,240" />
    <line start="RSVOR" end="MISTK" arrows="end" stroke="1-1-2-8" color="80,200,240" />
    <line start="MISTK" end="GRIFI" arrows="end" stroke="1-1-2-8" color="80,200,240" />
    <line start="GRIFI" end="GGABE" arrows="end" stroke="1-1-2-8" color="80,200,240" />
    <line start="GGABE" end="JOBEE" arrows="end" stroke="1-1-2-8" color="80,200,240" />
  </route>

  <route name="QUABN3" displayMode="star" zoomMin="8" zoomMax="600" color="160,200,240">
    <activeLandingRunways>27</activeLandingRunways>
    <navaids>QUABN,RSVOR,MISTK,REVER,FAKKE</navaids>
    <line start="QUABN" end="RSVOR" arrows="end" stroke="1-7-2-2" color="140,80,240" />
    <line start="RSVOR" end="MISTK" arrows="end" stroke="1-7-2-2" color="140,80,240" />
    <line start="MISTK" end="REVER" arrows="end" stroke="1-7-2-2" color="140,80,240" />
    <line start="REVER" end="FAKKE" arrows="end" stroke="1-7-2-2" color="140,80,240" />
  </route>

  <route name="QUABN3" displayMode="star" zoomMin="8" zoomMax="600" color="160,200,240">
    <activeLandingRunways>33L</activeLandingRunways>
    <navaids>QUABN,RSVOR,MISTK,BRODI,BECHH,SCITU</navaids>
    <line start="QUABN" end="RSVOR" arrows="end" stroke="1-6-2-3" color="140,140,240" />
    <line start="RSVOR" end="MISTK" arrows="end" stroke="1-6-2-3" color="140,140,240" />
    <line start="MISTK" end="BRODI" arrows="end" stroke="1-6-2-3" color="140,140,240" />
    <line start="BRODI" end="BECHH" arrows="end" stroke="1-6-2-3" color="140,140,240" />
    <line start="BECHH" end="SCITU" arrows="end" stroke="1-6-2-3" color="140,140,240" />
  </route>

  <route name="QUABN3" displayMode="star" zoomMin="8" zoomMax="600" color="160,200,240">
    <activeLandingRunways>32</activeLandingRunways>
    <navaids>QUABN,RSVOR,MISTK,BRODI,BECHH,SCITU</navaids>
    <line start="QUABN" end="RSVOR" arrows="end" stroke="1-6-2-3" color="140,140,240" />
    <line start="RSVOR" end="MISTK" arrows="end" stroke="1-6-2-3" color="140,140,240" />
    <line start="MISTK" end="BRODI" arrows="end" stroke="1-6-2-3" color="140,140,240" />
    <line start="BRODI" end="BECHH" arrows="end" stroke="1-6-2-3" color="140,140,240" />
    <line start="BECHH" end="SCITU" arrows="end" stroke="1-6-2-3" color="140,140,240" />
  </route>

  <route name="ROBUC1" displayMode="star" zoomMin="8" zoomMax="600" color="160,200,240">
    <activeLandingRunways>04L</activeLandingRunways>
    <navaids>ROBUC,PROVI,JOODY,SOFEE,ERNEI,NUNZO</navaids>
    <line start="ROBUC" end="PROVI" arrows="end" stroke="1-5-2-4" color="140,200,240" />
    <line start="PROVI" end="JOODY" arrows="end" stroke="1-5-2-4" color="140,200,240" />
    <line start="JOODY" end="SOFEE" arrows="end" stroke="1-5-2-4" color="140,200,240" />
    <line start="SOFEE" end="ERNEI" arrows="end" stroke="1-5-2-4" color="140,200,240" />
    <line start="ERNEI" end="NUNZO" arrows="end" stroke="1-5-2-4" color="140,200,240" />
  </route>

  <route name="ROBUC1" displayMode="star" zoomMin="8" zoomMax="600" color="160,200,240">
    <activeLandingRunways>15R</activeLandingRunways>
    <navaids>ROBUC,PROVI,JOODY,SOFEE,ERNEI,NUNZO</navaids>
    <line start="ROBUC" end="PROVI" arrows="end" stroke="1-5-2-4" color="140,200,240" />
    <line start="PROVI" end="JOODY" arrows="end" stroke="1-5-2-4" color="140,200,240" />
    <line start="JOODY" end="SOFEE" arrows="end" stroke="1-5-2-4" color="140,200,240" />
    <line start="SOFEE" end="ERNEI" arrows="end" stroke="1-5-2-4" color="140,200,240" />
    <line start="ERNEI" end="NUNZO" arrows="end" stroke="1-5-2-4" color="140,200,240" />
  </route>

  <route name="ROBUC1" displayMode="star" zoomMin="8" zoomMax="600" color="160,200,240">
    <activeLandingRunways>04R</activeLandingRunways>
    <navaids>ROBUC,PROVI,JOODY,SOFEE,ERNEI,GOSHI</navaids>
    <line start="ROBUC" end="PROVI" arrows="end" stroke="1-4-2-5" color="20,20,240" />
    <line start="PROVI" end="JOODY" arrows="end" stroke="1-4-2-5" color="20,20,240" />
    <line start="JOODY" end="SOFEE" arrows="end" stroke="1-4-2-5" color="20,20,240" />
    <line start="SOFEE" end="ERNEI" arrows="end" stroke="1-4-2-5" color="20,20,240" />
    <line start="ERNEI" end="GOSHI" arrows="end" stroke="1-4-2-5" color="20,20,240" />
  </route>

  <route name="ROBUC1" displayMode="star" zoomMin="8" zoomMax="600" color="160,200,240">
    <activeLandingRunways>22L</activeLandingRunways>
    <navaids>ROBUC,PROVI,JOODY,KRANN,ANSLY,CRADL,KLEBB,ETHYN,PTRIK,TAALE</navaids>
    <line start="ROBUC" end="PROVI" arrows="end" stroke="1-3-2-6" color="20,80,240" />
    <line start="PROVI" end="JOODY" arrows="end" stroke="1-3-2-6" color="20,80,240" />
    <line start="JOODY" end="KRANN" arrows="end" stroke="1-3-2-6" color="20,80,240" />
    <line start="KRANN" end="ANSLY" arrows="end" stroke="1-3-2-6" color="20,80,240" />
    <line start="ANSLY" end="CRADL" arrows="end" stroke="1-3-2-6" color="20,80,240" />
    <line start="CRADL" end="KLEBB" arrows="end" stroke="1-3-2-6" color="20,80,240" />
    <line start="KLEBB" end="ETHYN" arrows="end" stroke="1-3-2-6" color="20,80,240" />
    <line start="ETHYN" end="PTRIK" arrows="end" stroke="1-3-2-6" color="20,80,240" />
    <line start="PTRIK" end="TAALE" arrows="end" stroke="1-3-2-6" color="20,80,240" />
  </route>

  <route name="ROBUC1" displayMode="star" zoomMin="8" zoomMax="600" color="160,200,240">
    <activeLandingRunways>22R</activeLandingRunways>
    <navaids>ROBUC,PROVI,JOODY,KRANN,ANSLY,CRADL,KLEBB,ETHYN,PTRIK,TAALE</navaids>
    <line start="ROBUC" end="PROVI" arrows="end" stroke="1-3-2-6" color="20,80,240" />
    <line start="PROVI" end="JOODY" arrows="end" stroke="1-3-2-6" color="20,80,240" />
    <line start="JOODY" end="KRANN" arrows="end" stroke="1-3-2-6" color="20,80,240" />
    <line start="KRANN" end="ANSLY" arrows="end" stroke="1-3-2-6" color="20,80,240" />
    <line start="ANSLY" end="CRADL" arrows="end" stroke="1-3-2-6" color="20,80,240" />
    <line start="CRADL" end="KLEBB" arrows="end" stroke="1-3-2-6" color="20,80,240" />
    <line start="KLEBB" end="ETHYN" arrows="end" stroke="1-3-2-6" color="20,80,240" />
    <line start="ETHYN" end="PTRIK" arrows="end" stroke="1-3-2-6" color="20,80,240" />
    <line start="PTRIK" end="TAALE" arrows="end" stroke="1-3-2-6" color="20,80,240" />
  </route>

  <route name="ROBUC1" displayMode="star" zoomMin="8" zoomMax="600" color="160,200,240">
    <activeLandingRunways>33L</activeLandingRunways>
    <navaids>ROBUC,PROVI,JOODY,KRANN,ANSLY,BEREI,BBOGG</navaids>
    <line start="ROBUC" end="PROVI" arrows="end" stroke="1-2-2-7" color="20,140,240" />
    <line start="PROVI" end="JOODY" arrows="end" stroke="1-2-2-7" color="20,140,240" />
    <line start="JOODY" end="KRANN" arrows="end" stroke="1-2-2-7" color="20,140,240" />
    <line start="KRANN" end="ANSLY" arrows="end" stroke="1-2-2-7" color="20,140,240" />
    <line start="ANSLY" end="BEREI" arrows="end" stroke="1-2-2-7" color="20,140,240" />
    <line start="BEREI" end="BBOGG" arrows="end" stroke="1-2-2-7" color="20,140,240" />
  </route>

  <route name="ROBUC1" displayMode="star" zoomMin="8" zoomMax="600" color="160,200,240">
    <activeLandingRunways>32</activeLandingRunways>
    <navaids>ROBUC,PROVI,JOODY,KRANN,ANSLY,BEREI,BBOGG</navaids>
    <line start="ROBUC" end="PROVI" arrows="end" stroke="1-2-2-7" color="20,140,240" />
    <line start="PROVI" end="JOODY" arrows="end" stroke="1-2-2-7" color="20,140,240" />
    <line start="JOODY" end="KRANN" arrows="end" stroke="1-2-2-7" color="20,140,240" />
    <line start="KRANN" end="ANSLY" arrows="end" stroke="1-2-2-7" color="20,140,240" />
    <line start="ANSLY" end="BEREI" arrows="end" stroke="1-2-2-7" color="20,140,240" />
    <line start="BEREI" end="BBOGG" arrows="end" stroke="1-2-2-7" color="20,140,240" />
  </route>

  <route name="ROBUC1" displayMode="star" zoomMin="8" zoomMax="600" color="160,200,240">
    <activeLandingRunways>27</activeLandingRunways>
    <navaids>ROBUC,PROVI,JOODY,KRANN,ANSLY,CRADL,KLEBB,HOKDU</navaids>
    <line start="ROBUC" end="PROVI" arrows="end" stroke="1-1-2-8" color="20,200,240" />
    <line start="PROVI" end="JOODY" arrows="end" stroke="1-1-2-8" color="20,200,240" />
    <line start="JOODY" end="KRANN" arrows="end" stroke="1-1-2-8" color="20,200,240" />
    <line start="KRANN" end="ANSLY" arrows="end" stroke="1-1-2-8" color="20,200,240" />
    <line start="ANSLY" end="CRADL" arrows="end" stroke="1-1-2-8" color="20,200,240" />
    <line start="CRADL" end="KLEBB" arrows="end" stroke="1-1-2-8" color="20,200,240" />
    <line start="KLEBB" end="HOKDU" arrows="end" stroke="1-1-2-8" color="20,200,240" />
  </route>

  <route name="NHANT.BLZZR2" displayMode="sid" zoomMin="8" zoomMax="600" color="240,200,160">
    <activeStartRunways>04L</activeStartRunways>
    <navaids>NHANT,HURBE,ORRRR,CHWDH,STEEM,DEDHM,BLZZR</navaids>
    <line start="NHANT" end="HURBE" arrows="end" stroke="1-7-2-2" color="240,80,80" />
    <line start="HURBE" end="ORRRR" arrows="end" stroke="1-7-2-2" color="240,80,80" />
    <line start="ORRRR" end="CHWDH" arrows="end" stroke="1-7-2-2" color="240,80,80" />
    <line start="CHWDH" end="STEEM" arrows="end" stroke="1-7-2-2" color="240,80,80" />
    <line start="STEEM" end="DEDHM" arrows="end" stroke="1-7-2-2" color="240,80,80" />
    <line start="DEDHM" end="BLZZR" arrows="end" stroke="1-7-2-2" color="240,80,80" />
  </route>

  <route name="NHANT.BLZZR2" displayMode="sid" zoomMin="8" zoomMax="600" color="240,200,160">
    <activeStartRunways>04R</activeStartRunways>
    <navaids>NHANT,HURBE,ORRRR,CHWDH,STEEM,DEDHM,BLZZR</navaids>
    <line start="NHANT" end="HURBE" arrows="end" stroke="1-7-2-2" color="240,80,80" />
    <line start="HURBE" end="ORRRR" arrows="end" stroke="1-7-2-2" color="240,80,80" />
    <line start="ORRRR" end="CHWDH" arrows="end" stroke="1-7-2-2" color="240,80,80" />
    <line start="CHWDH" end="STEEM" arrows="end" stroke="1-7-2-2" color="240,80,80" />
    <line start="STEEM" end="DEDHM" arrows="end" stroke="1-7-2-2" color="240,80,80" />
    <line start="DEDHM" end="BLZZR" arrows="end" stroke="1-7-2-2" color="240,80,80" />
  </route>

  <route name="CLAWW.BLZZR2" displayMode="sid" zoomMin="8" zoomMax="600" color="240,200,160">
    <activeStartRunways>09</activeStartRunways>
    <navaids>CLAWW,FENWY,GLLET,WYMTH,DEDHM,BLZZR</navaids>
    <line start="CLAWW" end="FENWY" arrows="end" stroke="1-6-2-3" color="240,80,140" />
    <line start="FENWY" end="GLLET" arrows="end" stroke="1-6-2-3" color="240,80,140" />
    <line start="GLLET" end="WYMTH" arrows="end" stroke="1-6-2-3" color="240,80,140" />
    <line start="WYMTH" end="DEDHM" arrows="end" stroke="1-6-2-3" color="240,80,140" />
    <line start="DEDHM" end="BLZZR" arrows="end" stroke="1-6-2-3" color="240,80,140" />
  </route>

  <route name="FOXXX.BLZZR2" displayMode="sid" zoomMin="8" zoomMax="600" color="240,200,160">
    <activeStartRunways>15R</activeStartRunways>
    <navaids>FOXXX,BRRRO,JAITE,HEWMO,KENWI,BLZZR</navaids>
    <line start="FOXXX" end="BRRRO" arrows="end" stroke="1-5-2-4" color="240,80,200" />
    <line start="BRRRO" end="JAITE" arrows="end" stroke="1-5-2-4" color="240,80,200" />
    <line start="JAITE" end="HEWMO" arrows="end" stroke="1-5-2-4" color="240,80,200" />
    <line start="HEWMO" end="KENWI" arrows="end" stroke="1-5-2-4" color="240,80,200" />
    <line start="KENWI" end="BLZZR" arrows="end" stroke="1-5-2-4" color="240,80,200" />
  </route>

  <route name="TJAYY.BLZZR2" displayMode="sid" zoomMin="8" zoomMax="600" color="240,200,160">
    <activeStartRunways>22L</activeStartRunways>
    <navaids>TJAYY,BRRRO,JAITE,HEWMO,KENWI,BLZZR</navaids>
    <line start="TJAYY" end="BRRRO" arrows="end" stroke="1-4-2-5" color="240,140,20" />
    <line start="BRRRO" end="JAITE" arrows="end" stroke="1-4-2-5" color="240,140,20" />
    <line start="JAITE" end="HEWMO" arrows="end" stroke="1-4-2-5" color="240,140,20" />
    <line start="HEWMO" end="KENWI" arrows="end" stroke="1-4-2-5" color="240,140,20" />
    <line start="KENWI" end="BLZZR" arrows="end" stroke="1-4-2-5" color="240,140,20" />
  </route>

  <route name="TJAYY.BLZZR2" displayMode="sid" zoomMin="8" zoomMax="600" color="240,200,160">
    <activeStartRunways>22R</activeStartRunways>
    <navaids>TJAYY,BRRRO,JAITE,HEWMO,KENWI,BLZZR</navaids>
    <line start="TJAYY" end="BRRRO" arrows="end" stroke="1-4-2-5" color="240,140,20" />
    <line start="BRRRO" end="JAITE" arrows="end" stroke="1-4-2-5" color="240,140,20" />
    <line start="JAITE" end="HEWMO" arrows="end" stroke="1-4-2-5" color="240,140,20" />
    <line start="HEWMO" end="KENWI" arrows="end" stroke="1-4-2-5" color="240,140,20" />
    <line start="KENWI" end="BLZZR" arrows="end" stroke="1-4-2-5" color="240,140,20" />
  </route>

  <route name="KIRAA.BLZZR2" displayMode="sid" zoomMin="8" zoomMax="600" color="240,200,160">
    <activeStartRunways>27</activeStartRunways>
    <navaids>KIRAA,BLZZR</navaids>
    <line start="KIRAA" end="BLZZR" arrows="end" stroke="1-3-2-6" color="240,220,80" />
  </route>

  <route name="TEKKK.BLZZR2" displayMode="sid" zoomMin="8" zoomMax="600" color="240,200,160">
    <activeStartRunways>33L</activeStartRunways>
    <navaids>TEKKK,EXXXX,BLZZR</navaids>
    <line start="TEKKK" end="EXXXX" arrows="end" stroke="1-2-2-7" color="240,140,140" />
    <line start="EXXXX" end="BLZZR" arrows="end" stroke="1-2-2-7" color="240,140,140" />
  </route>

  <route name="TJAYY.BRUWN3" displayMode="sid" zoomMin="8" zoomMax="600" color="240,200,160">
    <activeStartRunways>22L</activeStartRunways>
    <navaids>TJAYY,BRRRO,BUCYK,BRUWN</navaids>
    <line start="TJAYY" end="BRRRO" arrows="end" stroke="1-1-2-8" color="240,140,200" />
    <line start="BRRRO" end="BUCYK" arrows="end" stroke="1-1-2-8" color="240,140,200" />
    <line start="BUCYK" end="BRUWN" arrows="end" stroke="1-1-2-8" color="240,140,200" />
  </route>

  <route name="TJAYY.BRUWN3" displayMode="sid" zoomMin="8" zoomMax="600" color="240,200,160">
    <activeStartRunways>22R</activeStartRunways>
    <navaids>TJAYY,BRRRO,BUCYK,BRUWN</navaids>
    <line start="TJAYY" end="BRRRO" arrows="end" stroke="1-1-2-8" color="240,140,200" />
    <line start="BRRRO" end="BUCYK" arrows="end" stroke="1-1-2-8" color="240,140,200" />
    <line start="BUCYK" end="BRUWN" arrows="end" stroke="1-1-2-8" color="240,140,200" />
  </route>

  <route name="FOXXX.BRUWN3" displayMode="sid" zoomMin="8" zoomMax="600" color="240,200,160">
    <activeStartRunways>15R</activeStartRunways>
    <navaids>FOXXX,BRRRO,BUCYK,BRUWN</navaids>
    <line start="FOXXX" end="BRRRO" arrows="end" stroke="1-8-2-1" color="240,20,20" />
    <line start="BRRRO" end="BUCYK" arrows="end" stroke="1-8-2-1" color="240,20,20" />
    <line start="BUCYK" end="BRUWN" arrows="end" stroke="1-8-2-1" color="240,20,20" />
  </route>

  <route name="CLAWW.BRUWN3" displayMode="sid" zoomMin="8" zoomMax="600" color="240,200,160">
    <activeStartRunways>09</activeStartRunways>
    <navaids>CLAWW,FENWY,BUCYK,BRUWN</navaids>
    <line start="CLAWW" end="FENWY" arrows="end" stroke="1-7-2-2" color="240,20,80" />
    <line start="FENWY" end="BUCYK" arrows="end" stroke="1-7-2-2" color="240,20,80" />
    <line start="BUCYK" end="BRUWN" arrows="end" stroke="1-7-2-2" color="240,20,80" />
  </route>

  <route name="NHANT.BRUWN3" displayMode="sid" zoomMin="8" zoomMax="600" color="240,200,160">
    <activeStartRunways>04L</activeStartRunways>
    <navaids>NHANT,HURBE,ORRRR,FENWY,BUCYK,BRUWN</navaids>
    <line start="NHANT" end="HURBE" arrows="end" stroke="1-6-2-3" color="240,20,140" />
    <line start="HURBE" end="ORRRR" arrows="end" stroke="1-6-2-3" color="240,20,140" />
    <line start="ORRRR" end="FENWY" arrows="end" stroke="1-6-2-3" color="240,20,140" />
    <line start="FENWY" end="BUCYK" arrows="end" stroke="1-6-2-3" color="240,20,140" />
    <line start="BUCYK" end="BRUWN" arrows="end" stroke="1-6-2-3" color="240,20,140" />
  </route>

  <route name="NHANT.BRUWN3" displayMode="sid" zoomMin="8" zoomMax="600" color="240,200,160">
    <activeStartRunways>04R</activeStartRunways>
    <navaids>NHANT,HURBE,ORRRR,FENWY,BUCYK,BRUWN</navaids>
    <line start="NHANT" end="HURBE" arrows="end" stroke="1-6-2-3" color="240,20,140" />
    <line start="HURBE" end="ORRRR" arrows="end" stroke="1-6-2-3" color="240,20,140" />
    <line start="ORRRR" end="FENWY" arrows="end" stroke="1-6-2-3" color="240,20,140" />
    <line start="FENWY" end="BUCYK" arrows="end" stroke="1-6-2-3" color="240,20,140" />
    <line start="BUCYK" end="BRUWN" arrows="end" stroke="1-6-2-3" color="240,20,140" />
  </route>

  <route name="KIRAA.BRUWN3" displayMode="sid" zoomMin="8" zoomMax="600" color="240,200,160">
    <activeStartRunways>27</activeStartRunways>
    <navaids>KIRAA,COLYN,BEREI,BRUWN</navaids>
    <line start="KIRAA" end="COLYN" arrows="end" stroke="1-5-2-4" color="240,20,200" />
    <line start="COLYN" end="BEREI" arrows="end" stroke="1-5-2-4" color="240,20,200" />
    <line start="BEREI" end="BRUWN" arrows="end" stroke="1-5-2-4" color="240,20,200" />
  </route>

  <route name="TEKKK.BRUWN3" displayMode="sid" zoomMin="8" zoomMax="600" color="240,200,160">
    <activeStartRunways>33L</activeStartRunways>
    <navaids>TEKKK,COUSY,CBEAR,COLYN,BEREI,BRUWN</navaids>
    <line start="TEKKK" end="COUSY" arrows="end" stroke="1-4-2-5" color="240,80,20" />
    <line start="COUSY" end="CBEAR" arrows="end" stroke="1-4-2-5" color="240,80,20" />
    <line start="CBEAR" end="COLYN" arrows="end" stroke="1-4-2-5" color="240,80,20" />
    <line start="COLYN" end="BEREI" arrows="end" stroke="1-4-2-5" color="240,80,20" />
    <line start="BEREI" end="BRUWN" arrows="end" stroke="1-4-2-5" color="240,80,20" />
  </route>

  <route name="NHANT.CELTK3" displayMode="sid" zoomMin="8" zoomMax="600" color="240,200,160">
    <activeStartRunways>04L</activeStartRunways>
    <navaids>NHANT,HURBE,ORRRR,TONNI,CELTK</navaids>
    <line start="NHANT" end="HURBE" arrows="end" stroke="1-3-2-6" color="240,80,80" />
    <line start="HURBE" end="ORRRR" arrows="end" stroke="1-3-2-6" color="240,80,80" />
    <line start="ORRRR" end="TONNI" arrows="end" stroke="1-3-2-6" color="240,80,80" />
    <line start="TONNI" end="CELTK" arrows="end" stroke="1-3-2-6" color="240,80,80" />
  </route>

  <route name="NHANT.CELTK3" displayMode="sid" zoomMin="8" zoomMax="600" color="240,200,160">
    <activeStartRunways>04R</activeStartRunways>
    <navaids>NHANT,HURBE,ORRRR,TONNI,CELTK</navaids>
    <line start="NHANT" end="HURBE" arrows="end" stroke="1-3-2-6" color="240,80,80" />
    <line start="HURBE" end="ORRRR" arrows="end" stroke="1-3-2-6" color="240,80,80" />
    <line start="ORRRR" end="TONNI" arrows="end" stroke="1-3-2-6" color="240,80,80" />
    <line start="TONNI" end="CELTK" arrows="end" stroke="1-3-2-6" color="240,80,80" />
  </route>

  <route name="CLAWW.CELTK3" displayMode="sid" zoomMin="8" zoomMax="600" color="240,200,160">
    <activeStartRunways>09</activeStartRunways>
    <navaids>CLAWW,FENWY,SCOAR,CELTK</navaids>
    <line start="CLAWW" end="FENWY" arrows="end" stroke="1-2-2-7" color="240,80,140" />
    <line start="FENWY" end="SCOAR" arrows="end" stroke="1-2-2-7" color="240,80,140" />
    <line start="SCOAR" end="CELTK" arrows="end" stroke="1-2-2-7" color="240,80,140" />
  </route>

  <route name="FOXXX.CELTK3" displayMode="sid" zoomMin="8" zoomMax="600" color="240,200,160">
    <activeStartRunways>15R</activeStartRunways>
    <navaids>FOXXX,BRRRO,SCOAR,CELTK</navaids>
    <line start="FOXXX" end="BRRRO" arrows="end" stroke="1-1-2-8" color="240,80,200" />
    <line start="BRRRO" end="SCOAR" arrows="end" stroke="1-1-2-8" color="240,80,200" />
    <line start="SCOAR" end="CELTK" arrows="end" stroke="1-1-2-8" color="240,80,200" />
  </route>

  <route name="TJAYY.CELTK3" displayMode="sid" zoomMin="8" zoomMax="600" color="240,200,160">
    <activeStartRunways>22L</activeStartRunways>
    <navaids>TJAYY,BRRRO,SCOAR,CELTK</navaids>
    <line start="TJAYY" end="BRRRO" arrows="end" stroke="1-8-2-1" color="240,140,20" />
    <line start="BRRRO" end="SCOAR" arrows="end" stroke="1-8-2-1" color="240,140,20" />
    <line start="SCOAR" end="CELTK" arrows="end" stroke="1-8-2-1" color="240,140,20" />
  </route>

  <route name="TJAYY.CELTK3" displayMode="sid" zoomMin="8" zoomMax="600" color="240,200,160">
    <activeStartRunways>22R</activeStartRunways>
    <navaids>TJAYY,BRRRO,SCOAR,CELTK</navaids>
    <line start="TJAYY" end="BRRRO" arrows="end" stroke="1-8-2-1" color="240,140,20" />
    <line start="BRRRO" end="SCOAR" arrows="end" stroke="1-8-2-1" color="240,140,20" />
    <line start="SCOAR" end="CELTK" arrows="end" stroke="1-8-2-1" color="240,140,20" />
  </route>

  <route name="KIRAA.CELTK3" displayMode="sid" zoomMin="8" zoomMax="600" color="240,200,160">
    <activeStartRunways>27</activeStartRunways>
    <navaids>KIRAA,COLYN,CELTK</navaids>
    <line start="KIRAA" end="COLYN" arrows="end" stroke="1-7-2-2" color="240,220,80" />
    <line start="COLYN" end="CELTK" arrows="end" stroke="1-7-2-2" color="240,220,80" />
  </route>

  <route name="TEKKK.CELTK3" displayMode="sid" zoomMin="8" zoomMax="600" color="240,200,160">
    <activeStartRunways>33L</activeStartRunways>
    <navaids>TEKKK,COUSY,CBEAR,COLYN,CELTK</navaids>
    <line start="TEKKK" end="COUSY" arrows="end" stroke="1-6-2-3" color="240,140,140" />
    <line start="COUSY" end="CBEAR" arrows="end" stroke="1-6-2-3" color="240,140,140" />
    <line start="CBEAR" end="COLYN" arrows="end" stroke="1-6-2-3" color="240,140,140" />
    <line start="COLYN" end="CELTK" arrows="end" stroke="1-6-2-3" color="240,140,140" />
  </route>

  <route name="NHANT.HYLND3" displayMode="sid" zoomMin="8" zoomMax="600" color="240,200,160">
    <activeStartRunways>04L</activeStartRunways>
    <navaids>NHANT,HURBE,STAYC,SHAAN,HYLND</navaids>
    <line start="NHANT" end="HURBE" arrows="end" stroke="1-5-2-4" color="240,140,200" />
    <line start="HURBE" end="STAYC" arrows="end" stroke="1-5-2-4" color="240,140,200" />
    <line start="STAYC" end="SHAAN" arrows="end" stroke="1-5-2-4" color="240,140,200" />
    <line start="SHAAN" end="HYLND" arrows="end" stroke="1-5-2-4" color="240,140,200" />
  </route>

  <route name="NHANT.HYLND3" displayMode="sid" zoomMin="8" zoomMax="600" color="240,200,160">
    <activeStartRunways>04R</activeStartRunways>
    <navaids>NHANT,HURBE,STAYC,SHAAN,HYLND</navaids>
    <line start="NHANT" end="HURBE" arrows="end" stroke="1-5-2-4" color="240,140,200" />
    <line start="HURBE" end="STAYC" arrows="end" stroke="1-5-2-4" color="240,140,200" />
    <line start="STAYC" end="SHAAN" arrows="end" stroke="1-5-2-4" color="240,140,200" />
    <line start="SHAAN" end="HYLND" arrows="end" stroke="1-5-2-4" color="240,140,200" />
  </route>

  <route name="CLAWW.HYLND3" displayMode="sid" zoomMin="8" zoomMax="600" color="240,200,160">
    <activeStartRunways>09</activeStartRunways>
    <navaids>CLAWW,CORRT,STAYC,HYLND</navaids>
    <line start="CLAWW" end="CORRT" arrows="end" stroke="1-4-2-5" color="240,20,20" />
    <line start="CORRT" end="STAYC" arrows="end" stroke="1-4-2-5" color="240,20,20" />
    <line start="STAYC" end="HYLND" arrows="end" stroke="1-4-2-5" color="240,20,20" />
  </route>

  <route name="FOXXX.HYLND3" displayMode="sid" zoomMin="8" zoomMax="600" color="240,200,160">
    <activeStartRunways>15R</activeStartRunways>
    <navaids>FOXXX,BOATT,HEARR,MARBB,HYLND</navaids>
    <line start="FOXXX" end="BOATT" arrows="end" stroke="1-3-2-6" color="240,20,80" />
    <line start="BOATT" end="HEARR" arrows="end" stroke="1-3-2-6" color="240,20,80" />
    <line start="HEARR" end="MARBB" arrows="end" stroke="1-3-2-6" color="240,20,80" />
    <line start="MARBB" end="HYLND" arrows="end" stroke="1-3-2-6" color="240,20,80" />
  </route>

  <route name="TJAYY.HYLND3" displayMode="sid" zoomMin="8" zoomMax="600" color="240,200,160">
    <activeStartRunways>22L</activeStartRunways>
    <navaids>TJAYY,BOATT,HEARR,MARBB,HYLND</navaids>
    <line start="TJAYY" end="BOATT" arrows="end" stroke="1-2-2-7" color="240,20,140" />
    <line start="BOATT" end="HEARR" arrows="end" stroke="1-2-2-7" color="240,20,140" />
    <line start="HEARR" end="MARBB" arrows="end" stroke="1-2-2-7" color="240,20,140" />
    <line start="MARBB" end="HYLND" arrows="end" stroke="1-2-2-7" color="240,20,140" />
  </route>

  <route name="TJAYY.HYLND3" displayMode="sid" zoomMin="8" zoomMax="600" color="240,200,160">
    <activeStartRunways>22R</activeStartRunways>
    <navaids>TJAYY,BOATT,HEARR,MARBB,HYLND</navaids>
    <line start="TJAYY" end="BOATT" arrows="end" stroke="1-2-2-7" color="240,20,140" />
    <line start="BOATT" end="HEARR" arrows="end" stroke="1-2-2-7" color="240,20,140" />
    <line start="HEARR" end="MARBB" arrows="end" stroke="1-2-2-7" color="240,20,140" />
    <line start="MARBB" end="HYLND" arrows="end" stroke="1-2-2-7" color="240,20,140" />
  </route>

  <route name="KIRAA.HYLND3" displayMode="sid" zoomMin="8" zoomMax="600" color="240,200,160">
    <activeStartRunways>27</activeStartRunways>
    <navaids>KIRAA,GLOWB,HRALD,HYLND</navaids>
    <line start="KIRAA" end="GLOWB" arrows="end" stroke="1-1-2-8" color="240,20,200" />
    <line start="GLOWB" end="HRALD" arrows="end" stroke="1-1-2-8" color="240,20,200" />
    <line start="HRALD" end="HYLND" arrows="end" stroke="1-1-2-8" color="240,20,200" />
  </route>

  <route name="TEKKK.HYLND3" displayMode="sid" zoomMin="8" zoomMax="600" color="240,200,160">
    <activeStartRunways>33L</activeStartRunways>
    <navaids>TEKKK,CAMWI,HYLND</navaids>
    <line start="TEKKK" end="CAMWI" arrows="end" stroke="1-8-2-1" color="240,80,20" />
    <line start="CAMWI" end="HYLND" arrows="end" stroke="1-8-2-1" color="240,80,20" />
  </route>

  <route name="NHANT.LBSTA3" displayMode="sid" zoomMin="8" zoomMax="600" color="240,200,160">
    <activeStartRunways>04L</activeStartRunways>
    <navaids>NHANT,HURBE,STAYC,SHAUN,LBSTA</navaids>
    <line start="NHANT" end="HURBE" arrows="end" stroke="1-7-2-2" color="240,80,80" />
    <line start="HURBE" end="STAYC" arrows="end" stroke="1-7-2-2" color="240,80,80" />
    <line start="STAYC" end="SHAUN" arrows="end" stroke="1-7-2-2" color="240,80,80" />
    <line start="SHAUN" end="LBSTA" arrows="end" stroke="1-7-2-2" color="240,80,80" />
  </route>

  <route name="NHANT.LBSTA3" displayMode="sid" zoomMin="8" zoomMax="600" color="240,200,160">
    <activeStartRunways>04R</activeStartRunways>
    <navaids>NHANT,HURBE,STAYC,SHAUN,LBSTA</navaids>
    <line start="NHANT" end="HURBE" arrows="end" stroke="1-7-2-2" color="240,80,80" />
    <line start="HURBE" end="STAYC" arrows="end" stroke="1-7-2-2" color="240,80,80" />
    <line start="STAYC" end="SHAUN" arrows="end" stroke="1-7-2-2" color="240,80,80" />
    <line start="SHAUN" end="LBSTA" arrows="end" stroke="1-7-2-2" color="240,80,80" />
  </route>

  <route name="CLAWW.LBSTA3" displayMode="sid" zoomMin="8" zoomMax="600" color="240,200,160">
    <activeStartRunways>09</activeStartRunways>
    <navaids>CLAWW,CLMPP,SHAUN,LBSTA</navaids>
    <line start="CLAWW" end="CLMPP" arrows="end" stroke="1-6-2-3" color="240,80,140" />
    <line start="CLMPP" end="SHAUN" arrows="end" stroke="1-6-2-3" color="240,80,140" />
    <line start="SHAUN" end="LBSTA" arrows="end" stroke="1-6-2-3" color="240,80,140" />
  </route>

  <route name="FOXXX.LBSTA3" displayMode="sid" zoomMin="8" zoomMax="600" color="240,200,160">
    <activeStartRunways>15R</activeStartRunways>
    <navaids>FOXXX,BOATT,HEARR,SHAUN,LBSTA</navaids>
    <line start="FOXXX" end="BOATT" arrows="end" stroke="1-5-2-4" color="240,80,200" />
    <line start="BOATT" end="HEARR" arrows="end" stroke="1-5-2-4" color="240,80,200" />
    <line start="HEARR" end="SHAUN" arrows="end" stroke="1-5-2-4" color="240,80,200" />
    <line start="SHAUN" end="LBSTA" arrows="end" stroke="1-5-2-4" color="240,80,200" />
  </route>

  <route name="TJAYY.LBSTA3" displayMode="sid" zoomMin="8" zoomMax="600" color="240,200,160">
    <activeStartRunways>22L</activeStartRunways>
    <navaids>TJAYY,BOATT,HEARR,SHAUN,LBSTA</navaids>
    <line start="TJAYY" end="BOATT" arrows="end" stroke="1-4-2-5" color="240,140,20" />
    <line start="BOATT" end="HEARR" arrows="end" stroke="1-4-2-5" color="240,140,20" />
    <line start="HEARR" end="SHAUN" arrows="end" stroke="1-4-2-5" color="240,140,20" />
    <line start="SHAUN" end="LBSTA" arrows="end" stroke="1-4-2-5" color="240,140,20" />
  </route>

  <route name="TJAYY.LBSTA3" displayMode="sid" zoomMin="8" zoomMax="600" color="240,200,160">
    <activeStartRunways>22R</activeStartRunways>
    <navaids>TJAYY,BOATT,HEARR,SHAUN,LBSTA</navaids>
    <line start="TJAYY" end="BOATT" arrows="end" stroke="1-4-2-5" color="240,140,20" />
    <line start="BOATT" end="HEARR" arrows="end" stroke="1-4-2-5" color="240,140,20" />
    <line start="HEARR" end="SHAUN" arrows="end" stroke="1-4-2-5" color="240,140,20" />
    <line start="SHAUN" end="LBSTA" arrows="end" stroke="1-4-2-5" color="240,140,20" />
  </route>

  <route name="KIRAA.LBSTA3" displayMode="sid" zoomMin="8" zoomMax="600" color="240,200,160">
    <activeStartRunways>27</activeStartRunways>
    <navaids>KIRAA,GLOWB,HRALD,CAMWI,LBSTA</navaids>
    <line start="KIRAA" end="GLOWB" arrows="end" stroke="1-3-2-6" color="240,220,80" />
    <line start="GLOWB" end="HRALD" arrows="end" stroke="1-3-2-6" color="240,220,80" />
    <line start="HRALD" end="CAMWI" arrows="end" stroke="1-3-2-6" color="240,220,80" />
    <line start="CAMWI" end="LBSTA" arrows="end" stroke="1-3-2-6" color="240,220,80" />
  </route>

  <route name="TEKKK.LBSTA3" displayMode="sid" zoomMin="8" zoomMax="600" color="240,200,160">
    <activeStartRunways>33L</activeStartRunways>
    <navaids>TEKKK,CAMWI,LBSTA</navaids>
    <line start="TEKKK" end="CAMWI" arrows="end" stroke="1-2-2-7" color="240,140,140" />
    <line start="CAMWI" end="LBSTA" arrows="end" stroke="1-2-2-7" color="240,140,140" />
  </route>

  <route name="NHANT.PATSS3" displayMode="sid" zoomMin="8" zoomMax="600" color="240,200,160">
    <activeStartRunways>04L</activeStartRunways>
    <navaids>NHANT,HURBE,ORRRR,CHWDH,STEEM,DEDHM,PATSS</navaids>
    <line start="NHANT" end="HURBE" arrows="end" stroke="1-8-2-1" color="240,20,20" />
    <line start="HURBE" end="ORRRR" arrows="end" stroke="1-8-2-1" color="240,20,20" />
    <line start="ORRRR" end="CHWDH" arrows="end" stroke="1-8-2-1" color="240,20,20" />
    <line start="CHWDH" end="STEEM" arrows="end" stroke="1-8-2-1" color="240,20,20" />
    <line start="STEEM" end="DEDHM" arrows="end" stroke="1-8-2-1" color="240,20,20" />
    <line start="DEDHM" end="PATSS" arrows="end" stroke="1-8-2-1" color="240,20,20" />
  </route>

  <route name="NHANT.PATSS3" displayMode="sid" zoomMin="8" zoomMax="600" color="240,200,160">
    <activeStartRunways>04R</activeStartRunways>
    <navaids>NHANT,HURBE,ORRRR,CHWDH,STEEM,DEDHM,PATSS</navaids>
    <line start="NHANT" end="HURBE" arrows="end" stroke="1-8-2-1" color="240,20,20" />
    <line start="HURBE" end="ORRRR" arrows="end" stroke="1-8-2-1" color="240,20,20" />
    <line start="ORRRR" end="CHWDH" arrows="end" stroke="1-8-2-1" color="240,20,20" />
    <line start="CHWDH" end="STEEM" arrows="end" stroke="1-8-2-1" color="240,20,20" />
    <line start="STEEM" end="DEDHM" arrows="end" stroke="1-8-2-1" color="240,20,20" />
    <line start="DEDHM" end="PATSS" arrows="end" stroke="1-8-2-1" color="240,20,20" />
  </route>

  <route name="CLAWW.PATSS3" displayMode="sid" zoomMin="8" zoomMax="600" color="240,200,160">
    <activeStartRunways>09</activeStartRunways>
    <navaids>CLAWW,FENWY,GLLET,WYMTH,DEDHM,PATSS</navaids>
    <line start="CLAWW" end="FENWY" arrows="end" stroke="1-7-2-2" color="240,20,80" />
    <line start="FENWY" end="GLLET" arrows="end" stroke="1-7-2-2" color="240,20,80" />
    <line start="GLLET" end="WYMTH" arrows="end" stroke="1-7-2-2" color="240,20,80" />
    <line start="WYMTH" end="DEDHM" arrows="end" stroke="1-7-2-2" color="240,20,80" />
    <line start="DEDHM" end="PATSS" arrows="end" stroke="1-7-2-2" color="240,20,80" />
  </route>

  <route name="FOXXX.PATSS3" displayMode="sid" zoomMin="8" zoomMax="600" color="240,200,160">
    <activeStartRunways>15R</activeStartRunways>
    <navaids>FOXXX,BRRRO,JAITE,HEWMO,KENWI,PATSS</navaids>
    <line start="FOXXX" end="BRRRO" arrows="end" stroke="1-6-2-3" color="240,20,140" />
    <line start="BRRRO" end="JAITE" arrows="end" stroke="1-6-2-3" color="240,20,140" />
    <line start="JAITE" end="HEWMO" arrows="end" stroke="1-6-2-3" color="240,20,140" />
    <line start="HEWMO" end="KENWI" arrows="end" stroke="1-6-2-3" color="240,20,140" />
    <line start="KENWI" end="PATSS" arrows="end" stroke="1-6-2-3" color="240,20,140" />
  </route>

  <route name="TJAYY.PATSS3" displayMode="sid" zoomMin="8" zoomMax="600" color="240,200,160">
    <activeStartRunways>22L</activeStartRunways>
    <navaids>TJAYY,BRRRO,JAITE,HEWMO,KENWI,PATSS</navaids>
    <line start="TJAYY" end="BRRRO" arrows="end" stroke="1-5-2-4" color="240,20,200" />
    <line start="BRRRO" end="JAITE" arrows="end" stroke="1-5-2-4" color="240,20,200" />
    <line start="JAITE" end="HEWMO" arrows="end" stroke="1-5-2-4" color="240,20,200" />
    <line start="HEWMO" end="KENWI" arrows="end" stroke="1-5-2-4" color="240,20,200" />
    <line start="KENWI" end="PATSS" arrows="end" stroke="1-5-2-4" color="240,20,200" />
  </route>

  <route name="TJAYY.PATSS3" displayMode="sid" zoomMin="8" zoomMax="600" color="240,200,160">
    <activeStartRunways>22R</activeStartRunways>
    <navaids>TJAYY,BRRRO,JAITE,HEWMO,KENWI,PATSS</navaids>
    <line start="TJAYY" end="BRRRO" arrows="end" stroke="1-5-2-4" color="240,20,200" />
    <line start="BRRRO" end="JAITE" arrows="end" stroke="1-5-2-4" color="240,20,200" />
    <line start="JAITE" end="HEWMO" arrows="end" stroke="1-5-2-4" color="240,20,200" />
    <line start="HEWMO" end="KENWI" arrows="end" stroke="1-5-2-4" color="240,20,200" />
    <line start="KENWI" end="PATSS" arrows="end" stroke="1-5-2-4" color="240,20,200" />
  </route>

  <route name="KIRAA.PATSS3" displayMode="sid" zoomMin="8" zoomMax="600" color="240,200,160">
    <activeStartRunways>27</activeStartRunways>
    <navaids>KIRAA,PATSS</navaids>
    <line start="KIRAA" end="PATSS" arrows="end" stroke="1-4-2-5" color="240,80,20" />
  </route>

  <route name="TEKKK.PATSS3" displayMode="sid" zoomMin="8" zoomMax="600" color="240,200,160">
    <activeStartRunways>33L</activeStartRunways>
    <navaids>TEKKK,COUSY,PATSS</navaids>
    <line start="TEKKK" end="COUSY" arrows="end" stroke="1-3-2-6" color="240,80,80" />
    <line start="COUSY" end="PATSS" arrows="end" stroke="1-3-2-6" color="240,80,80" />
  </route>

  <route name="NHANT.REVSS2" displayMode="sid" zoomMin="8" zoomMax="600" color="240,200,160">
    <activeStartRunways>04L</activeStartRunways>
    <navaids>NHANT,HURBE,ORRRR,CHWDH,STEEM,DEDHM,REVSS</navaids>
    <line start="NHANT" end="HURBE" arrows="end" stroke="1-2-2-7" color="240,80,140" />
    <line start="HURBE" end="ORRRR" arrows="end" stroke="1-2-2-7" color="240,80,140" />
    <line start="ORRRR" end="CHWDH" arrows="end" stroke="1-2-2-7" color="240,80,140" />
    <line start="CHWDH" end="STEEM" arrows="end" stroke="1-2-2-7" color="240,80,140" />
    <line start="STEEM" end="DEDHM" arrows="end" stroke="1-2-2-7" color="240,80,140" />
    <line start="DEDHM" end="REVSS" arrows="end" stroke="1-2-2-7" color="240,80,140" />
  </route>

  <route name="NHANT.REVSS2" displayMode="sid" zoomMin="8" zoomMax="600" color="240,200,160">
    <activeStartRunways>04R</activeStartRunways>
    <navaids>NHANT,HURBE,ORRRR,CHWDH,STEEM,DEDHM,REVSS</navaids>
    <line start="NHANT" end="HURBE" arrows="end" stroke="1-2-2-7" color="240,80,140" />
    <line start="HURBE" end="ORRRR" arrows="end" stroke="1-2-2-7" color="240,80,140" />
    <line start="ORRRR" end="CHWDH" arrows="end" stroke="1-2-2-7" color="240,80,140" />
    <line start="CHWDH" end="STEEM" arrows="end" stroke="1-2-2-7" color="240,80,140" />
    <line start="STEEM" end="DEDHM" arrows="end" stroke="1-2-2-7" color="240,80,140" />
    <line start="DEDHM" end="REVSS" arrows="end" stroke="1-2-2-7" color="240,80,140" />
  </route>

  <route name="CLAWW.REVSS2" displayMode="sid" zoomMin="8" zoomMax="600" color="240,200,160">
    <activeStartRunways>09</activeStartRunways>
    <navaids>CLAWW,FENWY,GLLET,WYMTH,DEDHM,REVSS</navaids>
    <line start="CLAWW" end="FENWY" arrows="end" stroke="1-1-2-8" color="240,80,200" />
    <line start="FENWY" end="GLLET" arrows="end" stroke="1-1-2-8" color="240,80,200" />
    <line start="GLLET" end="WYMTH" arrows="end" stroke="1-1-2-8" color="240,80,200" />
    <line start="WYMTH" end="DEDHM" arrows="end" stroke="1-1-2-8" color="240,80,200" />
    <line start="DEDHM" end="REVSS" arrows="end" stroke="1-1-2-8" color="240,80,200" />
  </route>

  <route name="FOXXX.REVSS2" displayMode="sid" zoomMin="8" zoomMax="600" color="240,200,160">
    <activeStartRunways>15R</activeStartRunways>
    <navaids>FOXXX,BRRRO,JAITE,HEWMO,KENWI,REVSS</navaids>
    <line start="FOXXX" end="BRRRO" arrows="end" stroke="1-8-2-1" color="240,140,20" />
    <line start="BRRRO" end="JAITE" arrows="end" stroke="1-8-2-1" color="240,140,20" />
    <line start="JAITE" end="HEWMO" arrows="end" stroke="1-8-2-1" color="240,140,20" />
    <line start="HEWMO" end="KENWI" arrows="end" stroke="1-8-2-1" color="240,140,20" />
    <line start="KENWI" end="REVSS" arrows="end" stroke="1-8-2-1" color="240,140,20" />
  </route>

  <route name="TJAYY.REVSS2" displayMode="sid" zoomMin="8" zoomMax="600" color="240,200,160">
    <activeStartRunways>22L</activeStartRunways>
    <navaids>TJAYY,BRRRO,JAITE,HEWMO,KENWI,REVSS</navaids>
    <line start="TJAYY" end="BRRRO" arrows="end" stroke="1-7-2-2" color="240,220,80" />
    <line start="BRRRO" end="JAITE" arrows="end" stroke="1-7-2-2" color="240,220,80" />
    <line start="JAITE" end="HEWMO" arrows="end" stroke="1-7-2-2" color="240,220,80" />
    <line start="HEWMO" end="KENWI" arrows="end" stroke="1-7-2-2" color="240,220,80" />
    <line start="KENWI" end="REVSS" arrows="end" stroke="1-7-2-2" color="240,220,80" />
  </route>

  <route name="TJAYY.REVSS2" displayMode="sid" zoomMin="8" zoomMax="600" color="240,200,160">
    <activeStartRunways>22R</activeStartRunways>
    <navaids>TJAYY,BRRRO,JAITE,HEWMO,KENWI,REVSS</navaids>
    <line start="TJAYY" end="BRRRO" arrows="end" stroke="1-7-2-2" color="240,220,80" />
    <line start="BRRRO" end="JAITE" arrows="end" stroke="1-7-2-2" color="240,220,80" />
    <line start="JAITE" end="HEWMO" arrows="end" stroke="1-7-2-2" color="240,220,80" />
    <line start="HEWMO" end="KENWI" arrows="end" stroke="1-7-2-2" color="240,220,80" />
    <line start="KENWI" end="REVSS" arrows="end" stroke="1-7-2-2" color="240,220,80" />
  </route>

  <route name="KIRAA.REVSS2" displayMode="sid" zoomMin="8" zoomMax="600" color="240,200,160">
    <activeStartRunways>27</activeStartRunways>
    <navaids>KIRAA,GLOWB,REVSS</navaids>
    <line start="KIRAA" end="GLOWB" arrows="end" stroke="1-6-2-3" color="240,140,140" />
    <line start="GLOWB" end="REVSS" arrows="end" stroke="1-6-2-3" color="240,140,140" />
  </route>

  <route name="TEKKK.REVSS2" displayMode="sid" zoomMin="8" zoomMax="600" color="240,200,160">
    <activeStartRunways>33L</activeStartRunways>
    <navaids>TEKKK,DUBYU,REVSS</navaids>
    <line start="TEKKK" end="DUBYU" arrows="end" stroke="1-5-2-4" color="240,140,200" />
    <line start="DUBYU" end="REVSS" arrows="end" stroke="1-5-2-4" color="240,140,200" />
  </route>

  <route name="NHANT.SSOXS3" displayMode="sid" zoomMin="8" zoomMax="600" color="240,200,160">
    <activeStartRunways>04L</activeStartRunways>
    <navaids>NHANT,HURBE,ORRRR,FENWY,BUCYK,JSTER,SSOXS</navaids>
    <line start="NHANT" end="HURBE" arrows="end" stroke="1-4-2-5" color="240,20,20" />
    <line start="HURBE" end="ORRRR" arrows="end" stroke="1-4-2-5" color="240,20,20" />
    <line start="ORRRR" end="FENWY" arrows="end" stroke="1-4-2-5" color="240,20,20" />
    <line start="FENWY" end="BUCYK" arrows="end" stroke="1-4-2-5" color="240,20,20" />
    <line start="BUCYK" end="JSTER" arrows="end" stroke="1-4-2-5" color="240,20,20" />
    <line start="JSTER" end="SSOXS" arrows="end" stroke="1-4-2-5" color="240,20,20" />
  </route>

  <route name="NHANT.SSOXS3" displayMode="sid" zoomMin="8" zoomMax="600" color="240,200,160">
    <activeStartRunways>04R</activeStartRunways>
    <navaids>NHANT,HURBE,ORRRR,FENWY,BUCYK,JSTER,SSOXS</navaids>
    <line start="NHANT" end="HURBE" arrows="end" stroke="1-4-2-5" color="240,20,20" />
    <line start="HURBE" end="ORRRR" arrows="end" stroke="1-4-2-5" color="240,20,20" />
    <line start="ORRRR" end="FENWY" arrows="end" stroke="1-4-2-5" color="240,20,20" />
    <line start="FENWY" end="BUCYK" arrows="end" stroke="1-4-2-5" color="240,20,20" />
    <line start="BUCYK" end="JSTER" arrows="end" stroke="1-4-2-5" color="240,20,20" />
    <line start="JSTER" end="SSOXS" arrows="end" stroke="1-4-2-5" color="240,20,20" />
  </route>

  <route name="CLAWW.SSOXS3" displayMode="sid" zoomMin="8" zoomMax="600" color="240,200,160">
    <activeStartRunways>09</activeStartRunways>
    <navaids>CLAWW,FENWY,BUCYK,JSTER,SSOXS</navaids>
    <line start="CLAWW" end="FENWY" arrows="end" stroke="1-3-2-6" color="240,20,80" />
    <line start="FENWY" end="BUCYK" arrows="end" stroke="1-3-2-6" color="240,20,80" />
    <line start="BUCYK" end="JSTER" arrows="end" stroke="1-3-2-6" color="240,20,80" />
    <line start="JSTER" end="SSOXS" arrows="end" stroke="1-3-2-6" color="240,20,80" />
  </route>

  <route name="FOXXX.SSOXS3" displayMode="sid" zoomMin="8" zoomMax="600" color="240,200,160">
    <activeStartRunways>15R</activeStartRunways>
    <navaids>FOXXX,BRRRO,BUCYK,JSTER,SSOXS</navaids>
    <line start="FOXXX" end="BRRRO" arrows="end" stroke="1-2-2-7" color="240,20,140" />
    <line start="BRRRO" end="BUCYK" arrows="end" stroke="1-2-2-7" color="240,20,140" />
    <line start="BUCYK" end="JSTER" arrows="end" stroke="1-2-2-7" color="240,20,140" />
    <line start="JSTER" end="SSOXS" arrows="end" stroke="1-2-2-7" color="240,20,140" />
  </route>

  <route name="TJAYY.SSOXS3" displayMode="sid" zoomMin="8" zoomMax="600" color="240,200,160">
    <activeStartRunways>22L</activeStartRunways>
    <navaids>TJAYY,BRRRO,BUCYK,JSTER,SSOXS</navaids>
    <line start="TJAYY" end="BRRRO" arrows="end" stroke="1-1-2-8" color="240,20,200" />
    <line start="BRRRO" end="BUCYK" arrows="end" stroke="1-1-2-8" color="240,20,200" />
    <line start="BUCYK" end="JSTER" arrows="end" stroke="1-1-2-8" color="240,20,200" />
    <line start="JSTER" end="SSOXS" arrows="end" stroke="1-1-2-8" color="240,20,200" />
  </route>

  <route name="TJAYY.SSOXS3" displayMode="sid" zoomMin="8" zoomMax="600" color="240,200,160">
    <activeStartRunways>22R</activeStartRunways>
    <navaids>TJAYY,BRRRO,BUCYK,JSTER,SSOXS</navaids>
    <line start="TJAYY" end="BRRRO" arrows="end" stroke="1-1-2-8" color="240,20,200" />
    <line start="BRRRO" end="BUCYK" arrows="end" stroke="1-1-2-8" color="240,20,200" />
    <line start="BUCYK" end="JSTER" arrows="end" stroke="1-1-2-8" color="240,20,200" />
    <line start="JSTER" end="SSOXS" arrows="end" stroke="1-1-2-8" color="240,20,200" />
  </route>

  <route name="KIRAA.SSOXS3" displayMode="sid" zoomMin="8" zoomMax="600" color="240,200,160">
    <activeStartRunways>27</activeStartRunways>
    <navaids>KIRAA,COLYN,SSOXS</navaids>
    <line start="KIRAA" end="COLYN" arrows="end" stroke="1-8-2-1" color="240,80,20" />
    <line start="COLYN" end="SSOXS" arrows="end" stroke="1-8-2-1" color="240,80,20" />
  </route>

  <route name="TEKKK.SSOXS3" displayMode="sid" zoomMin="8" zoomMax="600" color="240,200,160">
    <activeStartRunways>33L</activeStartRunways>
    <navaids>TEKKK,COUSY,CBEAR,COLYN,SSOXS</navaids>
    <line start="TEKKK" end="COUSY" arrows="end" stroke="1-7-2-2" color="240,80,80" />
    <line start="COUSY" end="CBEAR" arrows="end" stroke="1-7-2-2" color="240,80,80" />
    <line start="CBEAR" end="COLYN" arrows="end" stroke="1-7-2-2" color="240,80,80" />
    <line start="COLYN" end="SSOXS" arrows="end" stroke="1-7-2-2" color="240,80,80" />
  </route>



  <!-- additions from Danten66 -->

    <!-- <route name="RW 4R STAR" zoomMin="10" zoomMax="100" color="120,140,120">
  		<activeLandingRunways>04R</activeLandingRunways>
  		<navaids>WINNI,NABBO,MILTT,IRSEW</navaids>
      <text position="WINNI" fontSize="10" text="4000 ft     "/>
      <text position="NABBO" fontSize="10" text="3000 ft     "/>
      <text position="MILTT" fontSize="10" text="1700 ft     "/>
      <text position="IRSEW" fontSize="10" text="700 ft     "/>
    </route>

    <route name="RW 22L STAR" zoomMin="10" zoomMax="100" color="120,140,120">
      <activeLandingRunways>22L</activeLandingRunways>
      <navaids>NOLEY,WYANE,VOCUS,ZUMOL</navaids>
      <text position="NOLEY" fontSize="10" text="4000 ft     "/>
      <text position="WYANE" fontSize="10" text="3000 ft     "/>
      <text position="VOCUS" fontSize="10" text="1700 ft     "/>
      <text position="ZUMOL" fontSize="10" text="700 ft     "/>
    </route>

    <route name="RW 15R STAR" zoomMin="10" zoomMax="100" color="120,140,120">
      <activeLandingRunways>15R</activeLandingRunways>
      <navaids>SWIGG,WOBUR,MALDY</navaids>
      <text position=".4NM240@SWIGG" alignHeading="150" fontSize="10" text="4000 ft"/>
      <text position=".4NM240@WOBUR" alignHeading="150" fontSize="10" text="3000 ft"/>
      <text position=".4NM240@MALDY" alignHeading="150" fontSize="10" text="1700 ft"/>
      <line start="KBOS-RW33L" end="SWIGG" endOffset="-1.0" stroke="dots,2" text="ILS 15R" />
      <multiPointLine close="false" stroke="dots,1">
        <point>2.121NM40.531@SWIGG</point>
        <point>1NM015@SWIGG</point>
        <point>SWIGG</point>
        <point>1NM285@SWIGG</point>
        <point>2.121NM259.469@SWIGG</point>
         2.121nm70.531
      </multiPointLine>
    </route>
   -->
  <!-- SIDS -->

  <route name="RW 4R SID LOGAN 1" zoomMin="10" zoomMax="100" color="120,140,120">
    <activeStartRunways>04R</activeStartRunways>
    <line start="KBOS-RW04R" end="42.422976,-70.974174" stroke="dashed,1" text="036" />
    <line start="42.422976,-70.974174" angle="090" length="3.0" stroke="dashed,1" text="090" />
    <text position="42.422976,-70.974174" fontSize="11" clickable="true" text="4 DME - BOS"/>
    <!-- <text position="42.385841,-70.905295" fontSize="11" clickable="true" text="Runway 04R LOGAN ONE Departure. Climb heading 036 to BOS 4 DME, then turn right heading 090. Maintain 5000."/> -->
  </route>

  <route name="RW 4L SID LOGAN 1" zoomMin="10" zoomMax="100" color="120,140,120">
    <activeStartRunways>04L</activeStartRunways>
    <line start="KBOS-RW04L" end="42.423511,-70.980053" stroke="dashed,1" text="036" />
    <line start="42.423511,-70.980053" angle="090" length="3.0" stroke="dashed,1" text="090" />
    <text position="42.423511,-70.980053" fontSize="11" clickable="true" text="4 DME - BOS"/>
    <!-- <text position="42.419369,-71.043466" fontSize="11" clickable="true" text="Runway 04L LOGAN ONE Departure. Climb heading 036 to BOS 4 DME, then turn right heading 090. Maintain 5000."/> -->
    <!-- <line start="KBOS-RW04L" angle="036" length="4.0" stroke="dashed,1" text="036" /> -->
  </route>

  <route name="RW 22R SID LOGAN 1" zoomMin="10" zoomMax="100" color="120,140,120">
      <activeStartRunways>22R</activeStartRunways>
      <intercept startTurn="KBOS-RW22R" startHeading="216" direction="left" endHeading="140" end="TJAYY" stroke="dashed,1" text="140" />
      <!-- <intercept startTurn="KBOS-RW22R" startHeading="216" direction="left" endHeading="140" end="0.25NM216@13027" stroke="dashed,1" text="140" /> -->
  </route>

  <route name="RW 22L SID LOGAN 1" zoomMin="10" zoomMax="100" color="120,140,120">
      <activeStartRunways>22L</activeStartRunways>
      <intercept startTurn="KBOS-RW22L" startHeading="216" direction="left" endHeading="140" end="TJAYY" stroke="dashed,1" text="140" />
      <!-- <intercept startTurn="KBOS-RW22L" startHeading="216" direction="left" endHeading="140" end="0.25NM036@13027" stroke="dashed,1" text="140" /> -->
  </route>


  <route name="BOS DME Radial" color="150,150,150">
    <bow center="BOS" radius="4" startAngle="270" extentAngle="360" stroke="dots,1" text="4 dme"/>
    <bow center="BOS" radius="3" startAngle="270" extentAngle="360" stroke="dots,1" text="3 dme"/>
    <bow center="BOS" radius="2" startAngle="270" extentAngle="360" stroke="dots,1" text="2 dme"/>
    <bow center="BOS" radius="1" startAngle="270" extentAngle="360" stroke="dots,1" text="1 dme"/>
        <!-- <line start="BOS" angle="020" length="4.0" stroke="solid,1" />
        <line start="BOS" angle="022" length="4.0" stroke="solid,1" />
        <line start="BOS" angle="024" length="4.0" stroke="solid,1" />
        <line start="BOS" angle="026" length="4.0" stroke="solid,1" />
        <line start="BOS" angle="028" length="4.0" stroke="solid,1" />
        <line start="BOS" angle="030" length="4.0" stroke="solid,1" /> -->
  </route>










</routes>
